boseapi/__init__.py
boseapi/all.py
boseapi/client.py
boseapi/firmware.py
boseapi/model.py
boseapi/common/__init__.py
boseapi/common/device.py
boseapi/common/message.py
boseapi/common/nodes.py
boseapi/ws/__init__.py
boseapi/ws/bosews.py
boseapi-0.2.0.dist-info/LICENSE
boseapi-0.2.0.dist-info/METADATA
boseapi-0.2.0.dist-info/WHEEL
boseapi-0.2.0.dist-info/top_level.txt
boseapi-0.2.0.dist-info/RECORD
